Workbook

Sheet Monthly schedule
A1: Monthly Schedule
A3: Month | B3: Bradesco | C3: Itaú Mastercard | D3: Santander | E3: Family Card | F3: Total Cards | G3: Remaining Scheduled Payments | H3: Notes
A4: Jul/2026 | B4: 0 | C4: 0 | D4: 3136.83 | E4: 5253.5 | F4: =SUM(B4:E4) -> 8390.33 | G4: =SUM(F4:F16) -> 142370.7 | H4: July schedule reflects approved deferral of the two large personal cards.
A5: Aug/2026 | B5: 9660.13 | C5: 6047.97 | D5: 2916.04 | E5: 2678.59 | F5: =SUM(B5:E5) -> 21302.73 | G5: =SUM(F5:F16) -> 133980.37 | H5: Bradesco reflects July bill after R$ 5,300 prepayment.
A6: Sep/2026 | B6: 14960.13 | C6: 5982.08 | D6: 2569.41 | E6: 1124.23 | F6: =SUM(B6:E6) -> 24635.85 | G6: =SUM(F6:F16) -> 112677.64 | H6: Largest scheduled card month.
A7: Oct/2026 | B7: 10503.16 | C7: 5982.08 | D7: 519.97 | E7: 986.98 | F7: =SUM(B7:E7) -> 17992.19 | G7: =SUM(F7:F16) -> 88041.79 | H7: Still requires variable income support.
A8: Nov/2026 | B8: 9252.47 | C8: 5834.65 | D8: 519.97 | E8: 970.9 | F8: =SUM(B8:E8) -> 16577.99 | G8: =SUM(F8:F16) -> 70049.6 | H8: Pressure remains high if no additional work continues.
A9: Dec/2026 | B9: 6817.79 | C9: 5780.66 | D9: 519.97 | E9: 293.4 | F9: =SUM(B9:E9) -> 13411.82 | G9: =SUM(F9:F16) -> 53471.61 | H9: Year-end salary bonus expected in cash-flow file.
A10: Jan/2027 | B10: 5227.45 | C10: 3495.65 | D10: 519.97 | E10: 293.4 | F10: =SUM(B10:E10) -> 9536.47 | G10: =SUM(F10:F16) -> 40059.79 | H10: Base schedule before any January deferral scenario.
A11: Feb/2027 | B11: 5227.45 | C11: 3156.13 | D11: 519.97 | E11: 44 | F11: =SUM(B11:E11) -> 8947.55 | G11: =SUM(F11:F16) -> 30523.32 | H11: February includes performance bonus and honorarium in cash-flow file.
A12: Mar/2027 | B12: 5227.45 | C12: 2414.99 | D12: 519.97 | E12: 44 | F12: =SUM(B12:E12) -> 8206.41 | G12: =SUM(F12:F16) -> 21575.77 | H12: Normalization begins.
A13: Apr/2027 | B13: 3930.42 | C13: 2414.99 | D13: 519.97 | E13: 44 | F13: =SUM(B13:E13) -> 6909.38 | G13: =SUM(F13:F16) -> 13369.36 | H13: Card burden materially lower.
A14: May/2027 | B14: 3930.42 | C14: 2009.59 | D14: 519.97 | E14: 0 | F14: =SUM(B14:E14) -> 6459.98 | G14: =SUM(F14:F16) -> 6459.98 | H14: Near end of scheduled card ladder.
A15: Jun/2027 | B15: 0 | C15: 0 | D15: 0 | E15: 0 | F15: =SUM(B15:E15) -> 0 | G15: =SUM(F15:F16) -> 0 | H15: No mapped legacy card obligations after May in source plan.
A16: Jul/2027 | B16: 0 | C16: 0 | D16: 0 | E16: 0 | F16: =SUM(B16:E16) -> 0 | G16: =SUM(F16:F16) -> 0 | H16: Clean month if no new debt is added.

Sheet January deferral
A1: January
A3: Month | B3: Bradesco | C3: Itaú Mastercard | D3: Santander | E3: Family Card | F3: Total Cards | G3: Remaining Scheduled Payments | H3: Notes
A4: Jul/2026 | B4: 0 | C4: 0 | D4: 3136.83 | E4: 5253.5 | F4: =SUM(B4:E4) -> 8390.33 | G4: =SUM(F4:F16) -> 142890.67 | H4: July schedule reflects approved deferral of the two large personal cards.
A5: Aug/2026 | B5: 9660.13 | C5: 6047.97 | D5: 2916.04 | E5: 2678.59 | F5: =SUM(B5:E5) -> 21302.73 | G5: =SUM(F5:F16) -> 134500.34 | H5: Bradesco reflects July bill after R$ 5,300 prepayment.
A6: Sep/2026 | B6: 14960.13 | C6: 5982.08 | D6: 2569.41 | E6: 1124.23 | F6: =SUM(B6:E6) -> 24635.85 | G6: =SUM(F6:F16) -> 113197.61 | H6: Largest scheduled card month.
A7: Oct/2026 | B7: 10503.16 | C7: 5982.08 | D7: 519.97 | E7: 986.98 | F7: =SUM(B7:E7) -> 17992.19 | G7: =SUM(F7:F16) -> 88561.76 | H7: Still requires variable income support.
A8: Nov/2026 | B8: 9252.47 | C8: 5834.65 | D8: 519.97 | E8: 970.9 | F8: =SUM(B8:E8) -> 16577.99 | G8: =SUM(F8:F16) -> 70569.57 | H8: Pressure remains high if no additional work continues.
A9: Dec/2026 | B9: 6817.79 | C9: 5780.66 | D9: 519.97 | E9: 293.4 | F9: =SUM(B9:E9) -> 13411.82 | G9: =SUM(F9:F16) -> 53991.58 | H9: Year-end salary bonus expected in cash-flow file.
A10: Jan/2027 | B10: 0 | C10: 0 | D10: 519.97 | E10: 293.4 | F10: =SUM(B10:E10) -> 813.37 | G10: =SUM(F10:F16) -> 40579.76 | H10: January deferral scenario: large personal cards deferred if issuer rule is satisfied.
A11: Feb/2027 | B11: 5227.45 | C11: 3495.65 | D11: 519.97 | E11: 44 | F11: =SUM(B11:E11) -> 9287.07 | G11: =SUM(F11:F16) -> 39766.39 | H11: January Itaú/Master amount moves into February in this scenario.
A12: Mar/2027 | B12: 5227.45 | C12: 3156.13 | D12: 519.97 | E12: 44 | F12: =SUM(B12:E12) -> 8947.55 | G12: =SUM(F12:F16) -> 30479.32 | H12: February Itaú/Master amount moves into March.
A13: Apr/2027 | B13: 5227.45 | C13: 2414.99 | D13: 519.97 | E13: 44 | F13: =SUM(B13:E13) -> 8206.41 | G13: =SUM(F13:F16) -> 21531.77 | H13: Scenario tail shifts one month later.
A14: May/2027 | B14: 3930.42 | C14: 2414.99 | D14: 519.97 | E14: 0 | F14: =SUM(B14:E14) -> 6865.38 | G14: =SUM(F14:F16) -> 13325.36 | H14: Scenario tail shifts one month later.
A15: Jun/2027 | B15: 3930.42 | C15: 2009.59 | D15: 519.97 | E15: 0 | F15: =SUM(B15:E15) -> 6459.98 | G15: =SUM(F15:F16) -> 6459.98 | H15: Final shifted month under January deferral scenario.
A16: Jul/2027 | B16: 0 | C16: 0 | D16: 0 | E16: 0 | F16: =SUM(B16:E16) -> 0 | G16: =SUM(F16:F16) -> 0 | H16: Clean month if no new debt is added.

Sheet Remaining balance
A1: Remaining Card Balance Comparison
A3: Month | B3: Base Total Cards | C3: Scenario Total Cards | D3: Scenario Benefit/(Cost) | E3: Interpretation
A4: Jul/2026 | B4: ='Monthly schedule'!F4 -> 8390.33 | C4: ='January deferral'!F4 -> 8390.33 | D4: =B4-C4 -> 0 | E4: =IF(D4>0,"Lower cash need this month",IF(D4<0,"Shifted cost from prior month","No difference")) -> No difference
A5: Aug/2026 | B5: ='Monthly schedule'!F5 -> 21302.73 | C5: ='January deferral'!F5 -> 21302.73 | D5: =B5-C5 -> 0 | E5: =IF(D5>0,"Lower cash need this month",IF(D5<0,"Shifted cost from prior month","No difference")) -> No difference
A6: Sep/2026 | B6: ='Monthly schedule'!F6 -> 24635.85 | C6: ='January deferral'!F6 -> 24635.85 | D6: =B6-C6 -> 0 | E6: =IF(D6>0,"Lower cash need this month",IF(D6<0,"Shifted cost from prior month","No difference")) -> No difference
A7: Oct/2026 | B7: ='Monthly schedule'!F7 -> 17992.19 | C7: ='January deferral'!F7 -> 17992.19 | D7: =B7-C7 -> 0 | E7: =IF(D7>0,"Lower cash need this month",IF(D7<0,"Shifted cost from prior month","No difference")) -> No difference
A8: Nov/2026 | B8: ='Monthly schedule'!F8 -> 16577.99 | C8: ='January deferral'!F8 -> 16577.99 | D8: =B8-C8 -> 0 | E8: =IF(D8>0,"Lower cash need this month",IF(D8<0,"Shifted cost from prior month","No difference")) -> No difference
A9: Dec/2026 | B9: ='Monthly schedule'!F9 -> 13411.82 | C9: ='January deferral'!F9 -> 13411.82 | D9: =B9-C9 -> 0 | E9: =IF(D9>0,"Lower cash need this month",IF(D9<0,"Shifted cost from prior month","No difference")) -> No difference
A10: Jan/2027 | B10: ='Monthly schedule'!F10 -> 9536.47 | C10: ='January deferral'!F10 -> 813.37 | D10: =B10-C10 -> 8723.1 | E10: =IF(D10>0,"Lower cash need this month",IF(D10<0,"Shifted cost from prior month","No difference")) -> Lower cash need this month
A11: Feb/2027 | B11: ='Monthly schedule'!F11 -> 8947.55 | C11: ='January deferral'!F11 -> 9287.07 | D11: =B11-C11 -> -339.52 | E11: =IF(D11>0,"Lower cash need this month",IF(D11<0,"Shifted cost from prior month","No difference")) -> Shifted cost from prior month
A12: Mar/2027 | B12: ='Monthly schedule'!F12 -> 8206.41 | C12: ='January deferral'!F12 -> 8947.55 | D12: =B12-C12 -> -741.14 | E12: =IF(D12>0,"Lower cash need this month",IF(D12<0,"Shifted cost from prior month","No difference")) -> Shifted cost from prior month
A13: Apr/2027 | B13: ='Monthly schedule'!F13 -> 6909.38 | C13: ='January deferral'!F13 -> 8206.41 | D13: =B13-C13 -> -1297.03 | E13: =IF(D13>0,"Lower cash need this month",IF(D13<0,"Shifted cost from prior month","No difference")) -> Shifted cost from prior month
A14: May/2027 | B14: ='Monthly schedule'!F14 -> 6459.98 | C14: ='January deferral'!F14 -> 6865.38 | D14: =B14-C14 -> -405.4 | E14: =IF(D14>0,"Lower cash need this month",IF(D14<0,"Shifted cost from prior month","No difference")) -> Shifted cost from prior month
A15: Jun/2027 | B15: ='Monthly schedule'!F15 -> 0 | C15: ='January deferral'!F15 -> 6459.98 | D15: =B15-C15 -> -6459.98 | E15: =IF(D15>0,"Lower cash need this month",IF(D15<0,"Shifted cost from prior month","No difference")) -> Shifted cost from prior month
A16: Jul/2027 | B16: ='Monthly schedule'!F16 -> 0 | C16: ='January deferral'!F16 -> 0 | D16: =B16-C16 -> 0 | E16: =IF(D16>0,"Lower cash need this month",IF(D16<0,"Shifted cost from prior month","No difference")) -> No difference

Sheet Notes
A1: Remaining Card Balance Comparison
A3: Issue | B3: Treatment | C3: Planning Implication | D3: Advisor Caution
A4: July large card bills | B4: Recorded as deferred in the schedule | C4: Creates a strong July liquidity cushion | D4: Confirm the next due date in writing.
A5: January 2027 deferral | B5: Scenario only, not guaranteed | C5: Potentially reduces cash pressure before February bonus | D5: Do not treat as guaranteed relief unless issuer rule is confirmed.
A6: No new revolving credit | B6: Assumed in all schedules | C6: Keeps the card ladder declining | D6: Any new balance would invalidate the clean July 2027 view.
