Workbook

Sheet Confirmed income
A1: Variable income assumptions
A2: All monetary figures are in BRL unless a currency column says otherwise.
A3: Income Source | B3: Expected Month | C3: Amount | D3: Currency | E3: Exchange Rate | F3: BRL Estimate | G3: Status | H3: Confidence | I3: Notes
A4: MBA Tutoring | B4: Jul/2026 | C4: 1579.43 | D4: USD | E4: 5.184858 | F4: 8189.1203 | G4: Worked, pending/expected payment | H4: High | I4: Confirmed worked amount; do not assume recurring after July.
A5: Asset sale | B5: Jul/2026 | C5: 1375.62 | D5: BRL | E5: 1 | F5: 1375.62 | G5: Expected receipt | H5: High | I5: One-time cash receipt.
A6: Performance bonus | B6: Sep/2026 | C6: 10000 | D6: BRL | E6: 1 | F6: 10000 | G6: Expected | H6: Medium | I6: One-time annual/semester bonus.
A7: Year-end salary bonus | B7: Dec/2026 | C7: 5000 | D7: BRL | E7: 1 | F7: 5000 | G7: Expected | H7: Medium | I7: 13th salary net estimate.
A8: Performance bonus minimum | B8: Feb/2027 | C8: 20000 | D8: BRL | E8: 1 | F8: 20000 | G8: Expected | H8: Medium | I8: Minimum estimate for February bonus.
A9: Professional training honorarium | B9: Feb/2027 | C9: 7000 | D9: BRL | E9: 1 | F9: 7000 | G9: Expected | H9: Medium | I9: Separate one-time honorarium.

Sheet English Lessons
A1: English Lessons
A3: Input | B3: Value | C3: Unit | D3: Formula / Basis | E3: Scenario Role | F3: Editable? | G3: Risk | H3: Notes
A4: Hourly rate | B4: 29 | C4: USD/hour | D4: Client planning rate | E4: Base case | F4: Yes | G4: Medium | H4: Modeled as tutoring/lessons, not guaranteed employment.
A5: Weekly hours | B5: 16 | C5: hours/week | D5: Minimum target | E5: Base case | F5: Yes | G5: Medium | H5: Quality must be preserved; do not overcommit.
A6: Exchange rate | B6: 4.9594211 | C6: BRL/USD | D6: Observed recent payment conversion | E6: Base case | F6: Yes | G6: FX | H6: Use as planning estimate only.
A7: Weekly BRL estimate | B7: =B4*B5*B6 -> 2301.1714 | C7: BRL/week | D7: rate * hours * exchange rate | E7: Calculated | F7: No | G7: Formula | H7: Used by cash-flow model.

Sheet MBA Tutoring
A1: MBA Tutoring
A3: Month | B3: Legacy Expectation | C3: Current Confirmed Amount | D3: Currency | E3: BRL Estimate | F3: Use in Base Case? | G3: Notes
A4: Jul/2026 | B4: Payment expected | C4: 1579.43 | D4: USD | E4: =C4*'Confirmed income'!E4 -> 8189.1203 | F4: Yes | G4: Only confirmed month.
A5: Aug/2026 | B5: Potential continuation | C5: 0 | D5: USD | E5: 0 | F5: No | G5: Paused; do not assume income.
A6: Sep/2026 | B6: Potential continuation | C6: 0 | D6: USD | E6: 0 | F6: No | G6: Paused; upside scenario only.
A7: Oct/2026 | B7: Potential continuation | C7: 0 | D7: USD | E7: 0 | F7: No | G7: Paused; upside scenario only.

Sheet Bonuses
A1: Bonuses
A3: Income | B3: Month | C3: Amount | D3: Probability | E3: Risk Adjustment | F3: Risk-Weighted Amount
A4: Performance bonus | B4: Sep/2026 | C4: 10000 | D4: 0.85 | E4: Expected but not guaranteed | F4: =D4*C4 -> 8500
A5: Year-end salary bonus | B5: Dec/2026 | C5: 5000 | D5: 0.95 | E5: High confidence | F5: =D5*C5 -> 4750
A6: Performance bonus minimum | B6: Feb/2027 | C6: 20000 | D6: 0.8 | E6: Minimum estimate, still validate | F6: =D6*C6 -> 16000
A7: Professional training honorarium | B7: Feb/2027 | C7: 7000 | D7: 0.8 | E7: Expected separately | F7: =D7*C7 -> 5600

Sheet Scenario inputs
A1: Scenario
A3: Month | B3: English Lesson Weeks - Base | C3: English Lesson Income - Base | D3: English Lesson Weeks - Downside | E3: English Lesson Income - Downside | F3: English Lesson Weeks - Upside | G3: English Lesson Income - Upside
A4: Jul/2026 | B4: 5 | C4: =B4*'English Lessons'!$B$7 -> 11505.857 | D4: 5 | E4: =D4*'English Lessons'!$B$7 -> 11505.857 | F4: 5 | G4: =F4*'English Lessons'!$B$7 -> 11505.857
A5: Aug/2026 | B5: 4 | C5: =B5*'English Lessons'!$B$7 -> 9204.6856 | D5: 4 | E5: =D5*'English Lessons'!$B$7 -> 9204.6856 | F5: 4 | G5: =F5*'English Lessons'!$B$7 -> 9204.6856
A6: Sep/2026 | B6: 4 | C6: =B6*'English Lessons'!$B$7 -> 9204.6856 | D6: 0 | E6: 0 | F6: 4 | G6: =F6*'English Lessons'!$B$7 -> 9204.6856
A7: Oct/2026 | B7: 3 | C7: =B7*'English Lessons'!$B$7 -> 6903.5142 | D7: 0 | E7: 0 | F7: 4 | G7: =F7*'English Lessons'!$B$7 -> 9204.6856
A8: Nov/2026 | B8: 0 | C8: =B8*'English Lessons'!$B$7 -> 0 | D8: 0 | E8: 0 | F8: 4 | G8: =F8*'English Lessons'!$B$7 -> 9204.6856
A9: Dec/2026 | B9: 0 | C9: =B9*'English Lessons'!$B$7 -> 0 | D9: 0 | E9: 0 | F9: 4 | G9: =F9*'English Lessons'!$B$7 -> 9204.6856
A10: Jan/2027 | B10: 0 | C10: =B10*'English Lessons'!$B$7 -> 0 | D10: 0 | E10: 0 | F10: 4 | G10: =F10*'English Lessons'!$B$7 -> 9204.6856
